{
  "adult": false,
  "backdrop_path": "/uNRfK14Ga8Hwfqt07vo8nvWQN1i.jpg",
  "belongs_to_collection": {
    "id": 252313,
    "name": "The Endless Summer Collection",
    "poster_path": "/zhG3P4ALlXxoFi0CGfcVsR3qmDL.jpg",
    "backdrop_path": "/rbeqwDmy0yPMxBqA2ELvu08okcn.jpg"
  },
  "budget": 0,
  "genres": [{ "id": 99, "name": "Documentary" }],
  "homepage": "",
  "id": 21,
  "imdb_id": "tt0060371",
  "original_language": "en",
  "original_title": "The Endless Summer",
  "overview": "Bruce Brown's The Endless Summer is one of the first and most influential surf movies of all time. The film documents American surfers Mike Hynson and Robert August as they travel the world during California’s winter (which, back in 1965 was off-season for surfing) in search of the perfect wave and ultimately, an endless summer.",
  "popularity": 29.584,
  "poster_path": "/5W5uaqQ7NZTwoDMKO4AtdcahHex.jpg",
  "production_companies": [
    {
      "id": 13723,
      "logo_path": null,
      "name": "Bruce Brown Films",
      "origin_country": ""
    }
  ],
  "production_countries": [
    { "iso_3166_1": "US", "name": "United States of America" }
  ],
  "release_date": "1966-06-15",
  "revenue": 0,
  "runtime": 91,
  "spoken_languages": [
    { "english_name": "English", "iso_639_1": "en", "name": "English" }
  ],
  "status": "Released",
  "tagline": "The Search for the Perfect Wave!",
  "title": "The Endless Summer",
  "video": false,
  "vote_average": 7.374,
  "vote_count": 87
}
